{
    "product_id": "backpack_076",
    "product_name": "아동 하이킹 백팩 18L MH500",
    "model_description": "탐험용으로 또 통학용으로! 어린 등산가들을 위해 디자인한 똑똑한 조절식 가방입니다. 다양한 수납 구조로 편리하고 실용성이 뛰어납니다.  하루 일정의 등산에 적합한 18L 아동 백팩입니다.\n\n[백팩을 조절하는 방법]\n1 - 아이의 키에 맞게 등판 높이를 조절합니다(벨크로를 빼서 원하는 색상의 고리에 끼워 넣으세요). \n2 - 모든 스트랩을 느슨하게 풀어줍니다. (어깨끈, 벨트, 하중 조절 스트랩). \n3 - 백팩을 멥니다.  4 - 어깨끈을 조입니다. \n5 - 필요에 따라 하중 조절 스트랩을 조절합니다.\n\n[품질보증 기간 10년]\n품질보증은 제품의 모든 하자에 해당하며, 일반 사용으로 인한 마모 및 부적절한 사용으로 인한 손상은 해당하지 않습니다. 10년 품질보증은 구매한 제품과 구매 영수증이 있을 때 혜택받을 수 있습니다.본 상업적 보증은 제품을 구매한 국가 내의 법적 품질보증에 영향을 끼치지 않습니다.\n\n[제품 디자인, 데카트론만의 전문성]\n데카트론 디자인 팀은 프랑스 오뜨 사부아에 있는 몽블랑산 아래에 본사를 두고 있습니다. 이곳에서 일 년 열두 달, 심플하면서도 멋진 스타일의 최고의 기능성 제품을 개발합니다. 지속적인 제품 품질 향상을 위한 가장 좋은 방법은 실제 환경에서의 실험이라는 신념에 따라, 모든 제품에 철저한 현장 테스트를 시행합니다.\n\n[백팩 생산지]\n프랑스 몽블랑 산자락에 위치한 글로벌 디자인 센터에서의 제품 디자인 후, 중국 및 베트남의 공급업체를 통해 제작이 이루어집니다.\n데카트론은 제품 제작에 있어 전문성을 가진 공급업체들과 긴밀하게 협력하고 있습니다. \n공급업체와의 이러한 신뢰 관계를 바탕으로 고품질의 데카트론 제품이 생산됩니다.\n\n[보증 기간]\n10",
    "category": "모든 스포츠 > 등산 > 용품 > 가방 > 40L 이하",
    "variants": [
        {
            "color": "8787176",
            "image_paths": [
                "images/8787176/img1.png",
                "images/8787176/img2.png",
                "images/8787176/img3.png",
                "images/8787176/img4.png",
                "images/8787176/img5.png",
                "images/8787176/img6.png"
            ]
        }
    ]
}